lekvar/__init__.py
lekvar/containers.py
lekvar/lekvar.py
lekvar-0.0.5.dist-info/LICENSE
lekvar-0.0.5.dist-info/METADATA
lekvar-0.0.5.dist-info/WHEEL
lekvar-0.0.5.dist-info/top_level.txt
lekvar-0.0.5.dist-info/RECORD
