Metadata-Version: 2.1
Name: lekvar
Version: 0.0.5
Summary: Extended config parser with inheritance
Author: Zsombor Sándor
License: MIT License
Project-URL: Homepage, https://github.com/zombyguy/lekvar/
Project-URL: Repository, https://github.com/zombyguy/lekvar/
Project-URL: Issues, https://github.com/zombyguy/lekvar/issues
Keywords: lekvar,config,parse,configparser,inherit
Classifier: Development Status :: 3 - Alpha
Classifier: Intended Audience :: Developers
Classifier: Topic :: Software Development
Classifier: Topic :: Software Development :: Libraries
Classifier: License :: OSI Approved :: MIT License
Classifier: Operating System :: OS Independent
Classifier: Programming Language :: Python :: 3
Classifier: Programming Language :: Python :: 3.11
Classifier: Programming Language :: Python :: 3 :: Only
Requires-Python: >=3.11
License-File: LICENSE
